universal_log/__init__.py
universal_log/__init__.pyi
universal_log/py.typed
universal_log/sitecustomize.py
universal_log-0.1.1.dist-info/METADATA
universal_log-0.1.1.dist-info/WHEEL
universal_log-0.1.1.dist-info/top_level.txt
universal_log-0.1.1.dist-info/RECORD
