Metadata-Version: 2.4
Name: universal-log
Version: 0.1.1
Summary: Universal logger that adds console.log, System.out.println, and more globally to Python.
Home-page: https://github.com/yourusername/universal-log
Author: Your Name
Author-email: your@email.com
Classifier: Programming Language :: Python :: 3
Classifier: Typing :: Typed
Classifier: Operating System :: OS Independent
Requires-Python: >=3.6
Dynamic: author
Dynamic: author-email
Dynamic: classifier
Dynamic: description
Dynamic: description-content-type
Dynamic: home-page
Dynamic: requires-python
Dynamic: summary
